Users/Andrew Lorimer/AppData/Roaming/ppt-control/ppt-control.ini
ppt_control/__init__.py
ppt_control/__main__.py
ppt_control/config.py
ppt_control/http_server_39.py
ppt_control/ppt_control.py
ppt_control/ppt_control_obs.py
ppt_control/static/black.jpg
ppt_control/static/index.html
ppt_control/static/ppt-control.js
ppt_control/static/settings.js
ppt_control/static/style.css
ppt_control/static/white.jpg
ppt_control/static/icons/Thumbs.db
ppt_control/static/icons/Thumbs.db:encryptable
ppt_control/static/icons/first.svg
ppt_control/static/icons/last.svg
ppt_control/static/icons/left.svg
ppt_control/static/icons/ppt.ico
ppt_control/static/icons/ppt.png
ppt_control/static/icons/ppt_2.ico
ppt_control/static/icons/right.svg
ppt_control-0.0.4.dist-info/LICENSE
ppt_control-0.0.4.dist-info/METADATA
ppt_control-0.0.4.dist-info/WHEEL
ppt_control-0.0.4.dist-info/entry_points.txt
ppt_control-0.0.4.dist-info/top_level.txt
ppt_control-0.0.4.dist-info/RECORD
