Metadata-Version: 2.1
Name: ppt-control
Version: 0.0.4
Summary: Interface for controlling PowerPoint slideshows over WebSocket/HTTP
Home-page: https://git.lorimer.id.au/ppt-control.git
Author: Andrew Lorimer
Author-email: andrew@lorimer.id.au
License: UNKNOWN
Keywords: ppt-control ppt_control powerpoint ppt
Platform: UNKNOWN
Classifier: Development Status :: 4 - Beta
Classifier: Programming Language :: Python :: 3
Classifier: License :: OSI Approved :: GNU General Public License v3 (GPLv3)
Classifier: Operating System :: Microsoft :: Windows
Classifier: Topic :: Multimedia
Requires-Python: >=3.6
License-File: LICENSE
Requires-Dist: pywin32
Requires-Dist: websockets
Requires-Dist: pystray
